kvcommon/__init__.py
kvcommon/asynchronous/__init__.py
kvcommon/asynchronous/jobs/__init__.py
kvcommon/asynchronous/jobs/errors.py
kvcommon/asynchronous/jobs/event_loop.py
kvcommon/asynchronous/jobs/job.py
kvcommon/asynchronous/jobs/metrics.py
kvcommon/asynchronous/jobs/scheduler.py
kvcommon/asynchronous/jobs/status.py
kvcommon/asynchronous/utils.py
kvcommon/config/__init__.py
kvcommon/config/env.py
kvcommon/config/exceptions.py
kvcommon/config/validators.py
kvcommon/config/var.py
kvcommon/constants.py
kvcommon/datastore/__init__.py
kvcommon/datastore/backend.py
kvcommon/datastore/base.py
kvcommon/datetime.py
kvcommon/dict.py
kvcommon/exceptions.py
kvcommon/k8s/__init__.py
kvcommon/k8s/clients/__init__.py
kvcommon/k8s/clients/apps.py
kvcommon/k8s/clients/base.py
kvcommon/k8s/clients/core.py
kvcommon/k8s/clients/custom_objects.py
kvcommon/k8s/clients/networking.py
kvcommon/k8s/entities/__init__.py
kvcommon/k8s/entities/backendconfig.py
kvcommon/k8s/entities/base.py
kvcommon/k8s/entities/deployment.py
kvcommon/k8s/entities/iam.py
kvcommon/k8s/entities/ingress.py
kvcommon/k8s/entities/metadata.py
kvcommon/k8s/entities/pod_template.py
kvcommon/k8s/entities/secret.py
kvcommon/k8s/entities/serializable.py
kvcommon/k8s/entities/service.py
kvcommon/k8s/utils/gke.py
kvcommon/k8s/utils/network.py
kvcommon/k8s/utils/serialization.py
kvcommon/logger.py
kvcommon/misc/__init__.py
kvcommon/misc/entities.py
kvcommon/misc/shell.py
kvcommon/output.py
kvcommon/prometheus/__init__.py
kvcommon/prometheus/jobs.py
kvcommon/prometheus/utils.py
kvcommon/singleton.py
kvcommon/types.py
kvcommon/urls.py
kvcommon-0.4.9.dist-info/METADATA
kvcommon-0.4.9.dist-info/WHEEL
kvcommon-0.4.9.dist-info/licenses/LICENSE
kvcommon-0.4.9.dist-info/RECORD
