Metadata-Version: 2.4
Name: kvcommon
Version: 0.4.9
Summary: Library of miscellaneous common python utils that aren't worthy of their own dedicated libs.
License: MIT
License-File: LICENSE
Author: Rob Voigt
Author-email: code@ravoigt.com
Requires-Python: >=3.11,<4.0
Classifier: License :: OSI Approved :: MIT License
Classifier: Programming Language :: Python :: 3
Classifier: Programming Language :: Python :: 3.11
Classifier: Programming Language :: Python :: 3.12
Classifier: Programming Language :: Python :: 3.13
Classifier: Programming Language :: Python :: 3.14
Provides-Extra: k8s
Provides-Extra: prometheus
Requires-Dist: kubernetes (>=31.0.0,<32.0.0) ; extra == "k8s"
Requires-Dist: prometheus-client (>=0.20.0,<0.21.0) ; extra == "prometheus"
Requires-Dist: toml (>=0.10.2,<0.11.0)
Project-URL: Homepage, https://github.com/RAVoigt/kvcommon
Project-URL: Repository, https://github.com/RAVoigt/kvcommon
